ospark/__init__.py
ospark/backbone/__init__.py
ospark/backbone/auto_encoder.py
ospark/backbone/backbone.py
ospark/backbone/builder.py
ospark/backbone/resnet.py
ospark/backbone/u_net.py
ospark/backbone/vision_transformer.py
ospark/data/__init__.py
ospark/data/data_operator.py
ospark/data/encoder.py
ospark/data/folder.py
ospark/data/generator/__init__.py
ospark/data/generator/fots_data_generator.py
ospark/data/generator/translate_data_generator.py
ospark/data/path.py
ospark/data/save_delege.py
ospark/models/__init__.py
ospark/models/builder.py
ospark/models/coca.py
ospark/models/exdeep_transformer.py
ospark/models/former.py
ospark/models/informer.py
ospark/models/pixel_wise.py
ospark/models/text_recognition.py
ospark/models/transformer.py
ospark/nn/__init__.py
ospark/nn/block/__init__.py
ospark/nn/block/connection_block.py
ospark/nn/block/deep_transformer_block.py
ospark/nn/block/informer_block.py
ospark/nn/block/resnet_block.py
ospark/nn/block/transformer_block.py
ospark/nn/block/vgg_block.py
ospark/nn/cell/__init__.py
ospark/nn/cell/resnet_cell.py
ospark/nn/component/__init__.py
ospark/nn/component/basic_module.py
ospark/nn/component/name_space.py
ospark/nn/component/weight.py
ospark/nn/layers/__init__.py
ospark/nn/layers/activation.py
ospark/nn/layers/connection_layer.py
ospark/nn/layers/convolution_layer.py
ospark/nn/layers/deep_attention.py
ospark/nn/layers/deep_feed_forward.py
ospark/nn/layers/dense_layer.py
ospark/nn/layers/distilling_layer.py
ospark/nn/layers/embedding_layer.py
ospark/nn/layers/feed_forward.py
ospark/nn/layers/gated_linear_units.py
ospark/nn/layers/normalization.py
ospark/nn/layers/pooling_layer.py
ospark/nn/layers/prob_sparse.py
ospark/nn/layers/self_attention.py
ospark/nn/loss_function/__init__.py
ospark/nn/loss_function/balanced_loss.py
ospark/nn/loss_function/contrastive_loss.py
ospark/nn/loss_function/cross_entropy.py
ospark/nn/loss_function/degree_loss.py
ospark/nn/loss_function/dice_loss.py
ospark/nn/loss_function/focal_loss.py
ospark-0.1.4.dist-info/LICENSE.rst
ospark-0.1.4.dist-info/WHEEL
ospark-0.1.4.dist-info/METADATA
ospark-0.1.4.dist-info/RECORD
