Metadata-Version: 2.1
Name: ospark
Version: 0.1.4
Summary: Ospark is an opensource for quickly builder of former model series.
License: Apache-2.0
Keywords: text recognition,NLP,attention,tensorflow,transformer
Author: ospark-org
Author-email: donggicai1991@gmail.com
Requires-Python: >=3.7,<3.10
Classifier: Development Status :: 4 - Beta
Classifier: Intended Audience :: Developers
Classifier: Intended Audience :: Science/Research
Classifier: License :: OSI Approved :: Apache Software License
Classifier: Programming Language :: Python :: 3
Classifier: Programming Language :: Python :: 3 :: Only
Classifier: Programming Language :: Python :: 3.10
Classifier: Programming Language :: Python :: 3.7
Classifier: Programming Language :: Python :: 3.8
Classifier: Programming Language :: Python :: 3.9
Requires-Dist: tensorflow (>=2.12.0,<3.0.0)
